README.md
cells.py
gist.py
regex.py
setup.cfg
setup.py
ur.py
url_loader.py
gists/__init__.py
pclass/dircache.py
pclass/field.py
pclass/loader.py
ur.egg-info/PKG-INFO
ur.egg-info/SOURCES.txt
ur.egg-info/dependency_links.txt
ur.egg-info/requires.txt
ur.egg-info/top_level.txt