Metadata-Version: 2.1
Name: ur
Version: 0.1.2
Summary: Import remote Jupyter notebooks (or Python files)
Home-page: https://gitlab.com/runsascoded/ur
Author: Ryan Williams
Author-email: ryan@runsascoded.com
License: BSD
Keywords: gists,imports,importlib,jupyter,notebooks
Platform: UNKNOWN
Classifier: Programming Language :: Python :: 3
Classifier: License :: OSI Approved :: BSD License
Classifier: Operating System :: OS Independent
Requires-Python: >=3.3
